[
  {
    "id": "1",
    "name": "151 proof rum"
  },
  {
    "id": "2",
    "name": "7-up"
  },
  {
    "id": "3",
    "name": "absinthe"
  },
  {
    "id": "4",
    "name": "absolut citron"
  },
  {
    "id": "5",
    "name": "absolut kurant"
  },
  {
    "id": "6",
    "name": "absolut peppar"
  },
  {
    "id": "7",
    "name": "absolut vodka"
  },
  {
    "id": "8",
    "name": "advocaat"
  },
  {
    "id": "9",
    "name": "agave syrup"
  },
  {
    "id": "10",
    "name": "ale"
  },
  {
    "id": "11",
    "name": "allspice"
  },
  {
    "id": "12",
    "name": "almond"
  },
  {
    "id": "13",
    "name": "almond flavoring"
  },
  {
    "id": "14",
    "name": "amaretto"
  },
  {
    "id": "15",
    "name": "angelica root"
  },
  {
    "id": "16",
    "name": "angostura bitters"
  },
  {
    "id": "17",
    "name": "anis"
  },
  {
    "id": "18",
    "name": "anise"
  },
  {
    "id": "19",
    "name": "anisette"
  },
  {
    "id": "20",
    "name": "aperol"
  },
  {
    "id": "21",
    "name": "apfelkorn"
  },
  {
    "id": "22",
    "name": "apple"
  },
  {
    "id": "23",
    "name": "apple brandy"
  },
  {
    "id": "24",
    "name": "apple cider"
  },
  {
    "id": "25",
    "name": "apple juice"
  },
  {
    "id": "26",
    "name": "apple schnapps"
  },
  {
    "id": "27",
    "name": "applejack"
  },
  {
    "id": "28",
    "name": "apricot"
  },
  {
    "id": "29",
    "name": "apricot brandy"
  },
  {
    "id": "30",
    "name": "aquavit"
  },
  {
    "id": "31",
    "name": "asafoetida"
  },
  {
    "id": "32",
    "name": "añejo rum"
  },
  {
    "id": "33",
    "name": "bacardi limon"
  },
  {
    "id": "34",
    "name": "bailey"
  },
  {
    "id": "35",
    "name": "baileys irish cream"
  },
  {
    "id": "36",
    "name": "banana"
  },
  {
    "id": "37",
    "name": "banana liqueur"
  },
  {
    "id": "38",
    "name": "beer"
  },
  {
    "id": "39",
    "name": "benedictine"
  },
  {
    "id": "40",
    "name": "berries"
  },
  {
    "id": "41",
    "name": "bitter lemon"
  },
  {
    "id": "42",
    "name": "bitters"
  },
  {
    "id": "43",
    "name": "black pepper"
  },
  {
    "id": "44",
    "name": "black sambuca"
  },
  {
    "id": "45",
    "name": "blackberries"
  },
  {
    "id": "46",
    "name": "blackberry brandy"
  },
  {
    "id": "47",
    "name": "blackcurrant cordial"
  },
  {
    "id": "48",
    "name": "blackcurrant squash"
  },
  {
    "id": "49",
    "name": "blackstrap rum"
  },
  {
    "id": "50",
    "name": "blended scotch"
  },
  {
    "id": "51",
    "name": "blended whiskey"
  },
  {
    "id": "52",
    "name": "blue curacao"
  },
  {
    "id": "53",
    "name": "blueberry schnapps"
  },
  {
    "id": "54",
    "name": "bourbon"
  },
  {
    "id": "55",
    "name": "brandy"
  },
  {
    "id": "56",
    "name": "brown sugar"
  },
  {
    "id": "57",
    "name": "butter"
  },
  {
    "id": "58",
    "name": "butterscotch schnapps"
  },
  {
    "id": "59",
    "name": "cachaca"
  },
  {
    "id": "60",
    "name": "campari"
  },
  {
    "id": "61",
    "name": "candy"
  },
  {
    "id": "62",
    "name": "cantaloupe"
  },
  {
    "id": "63",
    "name": "caramel coloring"
  },
  {
    "id": "64",
    "name": "caramel sauce"
  },
  {
    "id": "65",
    "name": "carbonated soft drink"
  },
  {
    "id": "66",
    "name": "carbonated water"
  },
  {
    "id": "67",
    "name": "cardamom"
  },
  {
    "id": "68",
    "name": "carrot"
  },
  {
    "id": "69",
    "name": "cayenne pepper"
  },
  {
    "id": "70",
    "name": "celery salt"
  },
  {
    "id": "71",
    "name": "chambord raspberry liqueur"
  },
  {
    "id": "72",
    "name": "champagne"
  },
  {
    "id": "73",
    "name": "cherries"
  },
  {
    "id": "74",
    "name": "cherry"
  },
  {
    "id": "75",
    "name": "cherry brandy"
  },
  {
    "id": "76",
    "name": "cherry grenadine"
  },
  {
    "id": "77",
    "name": "cherry heering"
  },
  {
    "id": "78",
    "name": "cherry liqueur"
  },
  {
    "id": "79",
    "name": "chocolate"
  },
  {
    "id": "80",
    "name": "chocolate ice-cream"
  },
  {
    "id": "81",
    "name": "chocolate liqueur"
  },
  {
    "id": "82",
    "name": "chocolate milk"
  },
  {
    "id": "83",
    "name": "chocolate sauce"
  },
  {
    "id": "84",
    "name": "chocolate syrup"
  },
  {
    "id": "85",
    "name": "cider"
  },
  {
    "id": "86",
    "name": "cinnamon"
  },
  {
    "id": "87",
    "name": "cloves"
  },
  {
    "id": "88",
    "name": "club soda"
  },
  {
    "id": "89",
    "name": "coca-cola"
  },
  {
    "id": "90",
    "name": "cocoa powder"
  },
  {
    "id": "91",
    "name": "coconut liqueur"
  },
  {
    "id": "92",
    "name": "coconut milk"
  },
  {
    "id": "93",
    "name": "coconut rum"
  },
  {
    "id": "94",
    "name": "coconut syrup"
  },
  {
    "id": "95",
    "name": "coffee"
  },
  {
    "id": "96",
    "name": "coffee brandy"
  },
  {
    "id": "97",
    "name": "coffee liqueur"
  },
  {
    "id": "98",
    "name": "cognac"
  },
  {
    "id": "99",
    "name": "cointreau"
  },
  {
    "id": "100",
    "name": "condensed milk"
  },
  {
    "id": "101",
    "name": "coriander"
  },
  {
    "id": "102",
    "name": "corn syrup"
  },
  {
    "id": "103",
    "name": "cornstarch"
  },
  {
    "id": "104",
    "name": "corona"
  },
  {
    "id": "105",
    "name": "cranberries"
  },
  {
    "id": "106",
    "name": "cranberry juice"
  },
  {
    "id": "107",
    "name": "cranberry vodka"
  },
  {
    "id": "108",
    "name": "cream"
  },
  {
    "id": "109",
    "name": "cream of coconut"
  },
  {
    "id": "110",
    "name": "creme de banane"
  },
  {
    "id": "111",
    "name": "creme de cacao"
  },
  {
    "id": "112",
    "name": "creme de cassis"
  },
  {
    "id": "113",
    "name": "creme de mure"
  },
  {
    "id": "114",
    "name": "crown royal"
  },
  {
    "id": "115",
    "name": "cumin seed"
  },
  {
    "id": "116",
    "name": "curacao"
  },
  {
    "id": "117",
    "name": "daiquiri mix"
  },
  {
    "id": "118",
    "name": "dark creme de cacao"
  },
  {
    "id": "119",
    "name": "dark rum"
  },
  {
    "id": "120",
    "name": "demerara sugar"
  },
  {
    "id": "121",
    "name": "dr. pepper"
  },
  {
    "id": "122",
    "name": "drambuie"
  },
  {
    "id": "123",
    "name": "dry vermouth"
  },
  {
    "id": "124",
    "name": "dubonnet rouge"
  },
  {
    "id": "125",
    "name": "egg"
  },
  {
    "id": "126",
    "name": "egg white"
  },
  {
    "id": "127",
    "name": "egg yolk"
  },
  {
    "id": "128",
    "name": "elderflower cordial"
  },
  {
    "id": "129",
    "name": "erin cream"
  },
  {
    "id": "130",
    "name": "espresso"
  },
  {
    "id": "131",
    "name": "everclear"
  },
  {
    "id": "132",
    "name": "falernum"
  },
  {
    "id": "133",
    "name": "fennel seeds"
  },
  {
    "id": "134",
    "name": "firewater"
  },
  {
    "id": "135",
    "name": "food coloring"
  },
  {
    "id": "136",
    "name": "frangelico"
  },
  {
    "id": "137",
    "name": "fresca"
  },
  {
    "id": "138",
    "name": "fresh lemon juice"
  },
  {
    "id": "139",
    "name": "fresh lime juice"
  },
  {
    "id": "140",
    "name": "fruit"
  },
  {
    "id": "141",
    "name": "fruit juice"
  },
  {
    "id": "142",
    "name": "fruit punch"
  },
  {
    "id": "143",
    "name": "galliano"
  },
  {
    "id": "144",
    "name": "gin"
  },
  {
    "id": "145",
    "name": "ginger"
  },
  {
    "id": "146",
    "name": "ginger ale"
  },
  {
    "id": "147",
    "name": "ginger beer"
  },
  {
    "id": "148",
    "name": "ginger syrup"
  },
  {
    "id": "149",
    "name": "glycerine"
  },
  {
    "id": "150",
    "name": "godiva liqueur"
  },
  {
    "id": "151",
    "name": "gold rum"
  },
  {
    "id": "152",
    "name": "gold tequila"
  },
  {
    "id": "153",
    "name": "goldschlager"
  },
  {
    "id": "154",
    "name": "grain alcohol"
  },
  {
    "id": "155",
    "name": "grand marnier"
  },
  {
    "id": "156",
    "name": "grape juice"
  },
  {
    "id": "157",
    "name": "grape soda"
  },
  {
    "id": "158",
    "name": "grapefruit juice"
  },
  {
    "id": "159",
    "name": "grapes"
  },
  {
    "id": "160",
    "name": "green chartreuse"
  },
  {
    "id": "161",
    "name": "green creme de menthe"
  },
  {
    "id": "162",
    "name": "grenadine"
  },
  {
    "id": "163",
    "name": "guava juice"
  },
  {
    "id": "164",
    "name": "guinness stout"
  },
  {
    "id": "165",
    "name": "half-and-half"
  },
  {
    "id": "166",
    "name": "heavy cream"
  },
  {
    "id": "167",
    "name": "honey"
  },
  {
    "id": "168",
    "name": "honey syrup"
  },
  {
    "id": "169",
    "name": "hot chocolate"
  },
  {
    "id": "170",
    "name": "hot damn"
  },
  {
    "id": "171",
    "name": "ice"
  },
  {
    "id": "172",
    "name": "iced tea"
  },
  {
    "id": "173",
    "name": "irish cream"
  },
  {
    "id": "174",
    "name": "irish whiskey"
  },
  {
    "id": "175",
    "name": "islay single malt scotch"
  },
  {
    "id": "176",
    "name": "jack daniels"
  },
  {
    "id": "177",
    "name": "jagermeister"
  },
  {
    "id": "178",
    "name": "jello"
  },
  {
    "id": "179",
    "name": "jim beam"
  },
  {
    "id": "180",
    "name": "johnnie walker"
  },
  {
    "id": "181",
    "name": "jägermeister"
  },
  {
    "id": "182",
    "name": "kahlua"
  },
  {
    "id": "183",
    "name": "kirschwasser"
  },
  {
    "id": "184",
    "name": "kiwi"
  },
  {
    "id": "185",
    "name": "kiwi liqueur"
  },
  {
    "id": "186",
    "name": "kool-aid"
  },
  {
    "id": "187",
    "name": "kummel"
  },
  {
    "id": "188",
    "name": "lager"
  },
  {
    "id": "189",
    "name": "lavender"
  },
  {
    "id": "190",
    "name": "lemon"
  },
  {
    "id": "191",
    "name": "lemon juice"
  },
  {
    "id": "192",
    "name": "lemon peel"
  },
  {
    "id": "193",
    "name": "lemon vodka"
  },
  {
    "id": "194",
    "name": "lemon-lime soda"
  },
  {
    "id": "195",
    "name": "lemonade"
  },
  {
    "id": "196",
    "name": "licorice root"
  },
  {
    "id": "197",
    "name": "light cream"
  },
  {
    "id": "198",
    "name": "light rum"
  },
  {
    "id": "199",
    "name": "lillet"
  },
  {
    "id": "200",
    "name": "lillet blanc"
  },
  {
    "id": "201",
    "name": "lime"
  },
  {
    "id": "202",
    "name": "lime juice"
  },
  {
    "id": "203",
    "name": "lime juice cordial"
  },
  {
    "id": "204",
    "name": "lime peel"
  },
  {
    "id": "205",
    "name": "lime vodka"
  },
  {
    "id": "206",
    "name": "limeade"
  },
  {
    "id": "207",
    "name": "malibu rum"
  },
  {
    "id": "208",
    "name": "mango"
  },
  {
    "id": "209",
    "name": "maple syrup"
  },
  {
    "id": "210",
    "name": "maraschino cherry"
  },
  {
    "id": "211",
    "name": "maraschino liqueur"
  },
  {
    "id": "212",
    "name": "marjoram leaves"
  },
  {
    "id": "213",
    "name": "marshmallows"
  },
  {
    "id": "214",
    "name": "maui"
  },
  {
    "id": "215",
    "name": "melon liqueur"
  },
  {
    "id": "216",
    "name": "mezcal"
  },
  {
    "id": "217",
    "name": "midori melon liqueur"
  },
  {
    "id": "218",
    "name": "milk"
  },
  {
    "id": "219",
    "name": "mini-snickers bars"
  },
  {
    "id": "220",
    "name": "mint"
  },
  {
    "id": "221",
    "name": "mint syrup"
  },
  {
    "id": "222",
    "name": "mountain dew"
  },
  {
    "id": "223",
    "name": "nutmeg"
  },
  {
    "id": "224",
    "name": "olive"
  },
  {
    "id": "225",
    "name": "olive brine"
  },
  {
    "id": "226",
    "name": "orange"
  },
  {
    "id": "227",
    "name": "orange bitters"
  },
  {
    "id": "228",
    "name": "orange curacao"
  },
  {
    "id": "229",
    "name": "orange juice"
  },
  {
    "id": "230",
    "name": "orange peel"
  },
  {
    "id": "231",
    "name": "orange spiral"
  },
  {
    "id": "232",
    "name": "oreo cookie"
  },
  {
    "id": "233",
    "name": "orgeat syrup"
  },
  {
    "id": "234",
    "name": "ouzo"
  },
  {
    "id": "235",
    "name": "papaya"
  },
  {
    "id": "236",
    "name": "passion fruit juice"
  },
  {
    "id": "237",
    "name": "passion fruit syrup"
  },
  {
    "id": "238",
    "name": "passoa"
  },
  {
    "id": "239",
    "name": "peach bitters"
  },
  {
    "id": "240",
    "name": "peach brandy"
  },
  {
    "id": "241",
    "name": "peach nectar"
  },
  {
    "id": "242",
    "name": "peach schnapps"
  },
  {
    "id": "243",
    "name": "peach vodka"
  },
  {
    "id": "244",
    "name": "peachtree schnapps"
  },
  {
    "id": "245",
    "name": "pepper"
  },
  {
    "id": "246",
    "name": "peppermint extract"
  },
  {
    "id": "247",
    "name": "peppermint schnapps"
  },
  {
    "id": "248",
    "name": "pepsi cola"
  },
  {
    "id": "249",
    "name": "pernod"
  },
  {
    "id": "250",
    "name": "peychaud bitters"
  },
  {
    "id": "251",
    "name": "pina colada mix"
  },
  {
    "id": "252",
    "name": "pineapple"
  },
  {
    "id": "253",
    "name": "pineapple juice"
  },
  {
    "id": "254",
    "name": "pineapple syrup"
  },
  {
    "id": "255",
    "name": "pink lemonade"
  },
  {
    "id": "256",
    "name": "pisang ambon"
  },
  {
    "id": "257",
    "name": "pisco"
  },
  {
    "id": "258",
    "name": "port"
  },
  {
    "id": "259",
    "name": "powdered sugar"
  },
  {
    "id": "260",
    "name": "prosecco"
  },
  {
    "id": "261",
    "name": "raspberry liqueur"
  },
  {
    "id": "262",
    "name": "raspberry syrup"
  },
  {
    "id": "263",
    "name": "raspberry vodka"
  },
  {
    "id": "264",
    "name": "red wine"
  },
  {
    "id": "265",
    "name": "ricard"
  },
  {
    "id": "266",
    "name": "root beer"
  },
  {
    "id": "267",
    "name": "rosemary"
  },
  {
    "id": "268",
    "name": "rosso vermouth"
  },
  {
    "id": "269",
    "name": "rum"
  },
  {
    "id": "270",
    "name": "rumple minze"
  },
  {
    "id": "271",
    "name": "rye whiskey"
  },
  {
    "id": "272",
    "name": "salt"
  },
  {
    "id": "273",
    "name": "salted chocolate"
  },
  {
    "id": "274",
    "name": "sambuca"
  },
  {
    "id": "275",
    "name": "sarsaparilla"
  },
  {
    "id": "276",
    "name": "schweppes russchian"
  },
  {
    "id": "277",
    "name": "scotch"
  },
  {
    "id": "278",
    "name": "sherbet"
  },
  {
    "id": "279",
    "name": "sherry"
  },
  {
    "id": "280",
    "name": "sirup of roses"
  },
  {
    "id": "281",
    "name": "sloe gin"
  },
  {
    "id": "282",
    "name": "soda water"
  },
  {
    "id": "283",
    "name": "sour mix"
  },
  {
    "id": "284",
    "name": "southern comfort"
  },
  {
    "id": "285",
    "name": "spiced rum"
  },
  {
    "id": "286",
    "name": "sprite"
  },
  {
    "id": "287",
    "name": "st. germain"
  },
  {
    "id": "288",
    "name": "strawberries"
  },
  {
    "id": "289",
    "name": "strawberry liqueur"
  },
  {
    "id": "290",
    "name": "strawberry schnapps"
  },
  {
    "id": "291",
    "name": "sugar"
  },
  {
    "id": "292",
    "name": "sugar syrup"
  },
  {
    "id": "293",
    "name": "surge"
  },
  {
    "id": "294",
    "name": "sweet and sour"
  },
  {
    "id": "295",
    "name": "sweet vermouth"
  },
  {
    "id": "296",
    "name": "tabasco sauce"
  },
  {
    "id": "297",
    "name": "tea"
  },
  {
    "id": "298",
    "name": "tennessee whiskey"
  },
  {
    "id": "299",
    "name": "tequila"
  },
  {
    "id": "300",
    "name": "tia maria"
  },
  {
    "id": "301",
    "name": "tomato juice"
  },
  {
    "id": "302",
    "name": "tonic water"
  },
  {
    "id": "303",
    "name": "triple sec"
  },
  {
    "id": "304",
    "name": "tropicana"
  },
  {
    "id": "305",
    "name": "vanilla"
  },
  {
    "id": "306",
    "name": "vanilla extract"
  },
  {
    "id": "307",
    "name": "vanilla ice-cream"
  },
  {
    "id": "308",
    "name": "vanilla vodka"
  },
  {
    "id": "309",
    "name": "vermouth"
  },
  {
    "id": "310",
    "name": "vodka"
  },
  {
    "id": "311",
    "name": "water"
  },
  {
    "id": "312",
    "name": "whipped cream"
  },
  {
    "id": "313",
    "name": "whipping cream"
  },
  {
    "id": "314",
    "name": "whiskey"
  },
  {
    "id": "315",
    "name": "whisky"
  },
  {
    "id": "316",
    "name": "white creme de menthe"
  },
  {
    "id": "317",
    "name": "white rum"
  },
  {
    "id": "318",
    "name": "wild turkey"
  },
  {
    "id": "319",
    "name": "wine"
  },
  {
    "id": "320",
    "name": "worcestershire sauce"
  },
  {
    "id": "321",
    "name": "wormwood"
  },
  {
    "id": "322",
    "name": "yellow chartreuse"
  },
  {
    "id": "323",
    "name": "yoghurt"
  },
  {
    "id": "324",
    "name": "yukon jack"
  },
  {
    "id": "325",
    "name": "zima"
  }
]